seadog/__init__.py
seadog/cli.py
seadog-0.1.2.dist-info/entry_points.txt
seadog-0.1.2.dist-info/LICENSE
seadog-0.1.2.dist-info/WHEEL
seadog-0.1.2.dist-info/METADATA
seadog-0.1.2.dist-info/RECORD
