Metadata-Version: 2.1
Name: seadog
Version: 0.1.2
Summary: Statistical data visualization from the command line
Home-page: https://github.com/leonhfr/seadog
Author: leonhfr
Author-email: hello@leonh.fr
Requires-Python: >=3.7,<4.0
Classifier: Programming Language :: Python :: 3
Classifier: Programming Language :: Python :: 3.7
Classifier: Programming Language :: Python :: 3.8
Requires-Dist: click (>=7.0,<8.0)
Requires-Dist: matplotlib (>=3.1.2,<4.0.0)
Requires-Dist: numpy (>=1.18.0,<2.0.0)
Requires-Dist: pandas (>=0.25.3,<0.26.0)
Requires-Dist: seaborn (>=0.9.0,<0.10.0)
Requires-Dist: tabulate (>=0.8.6,<0.9.0)
Requires-Dist: termplotlib (>=0.2.3,<0.3.0)
Project-URL: Documentation, https://github.com/leonhfr/seadog
Project-URL: Repository, https://github.com/leonhfr/seadog
